LICENSE
MANIFEST.in
README.md
setup.py
djangocms_widgetbox.egg-info/PKG-INFO
djangocms_widgetbox.egg-info/SOURCES.txt
djangocms_widgetbox.egg-info/dependency_links.txt
djangocms_widgetbox.egg-info/requires.txt
djangocms_widgetbox.egg-info/top_level.txt
widgetbox/__init__.py
widgetbox/cms_plugins.py
widgetbox/models.py
widgetbox/settings.py
widgetbox/migrations/0001_initial.py
widgetbox/migrations/0002_faq_faqtopic.py
widgetbox/migrations/0003_auto_20150522_0959.py
widgetbox/migrations/0005_rename_model_button.py
widgetbox/migrations/0006_fix_cms_plugins_data.py
widgetbox/migrations/0007_auto_20150522_1634.py
widgetbox/migrations/0008_auto_20150710_1450.py
widgetbox/migrations/0009_divider.py
widgetbox/migrations/0010_html.py
widgetbox/migrations/0011_auto_20150731_0958.py
widgetbox/migrations/0012_auto_20150731_1019.py
widgetbox/migrations/0013_auto_20150731_1024.py
widgetbox/migrations/0014_auto_20160303_1007.py
widgetbox/migrations/0015_list_listitem.py
widgetbox/migrations/0016_list_style.py
widgetbox/migrations/0017_auto_20160303_1551.py
widgetbox/migrations/0018_backgroundimage.py
widgetbox/migrations/0019_tab_tabpane.py
widgetbox/migrations/0020_auto_20160304_1134.py
widgetbox/migrations/__init__.py
widgetbox/templates/widgetbox/background-image.html
widgetbox/templates/widgetbox/button.html
widgetbox/templates/widgetbox/column.html
widgetbox/templates/widgetbox/container.html
widgetbox/templates/widgetbox/divider.html
widgetbox/templates/widgetbox/faq-topic.html
widgetbox/templates/widgetbox/faq.html
widgetbox/templates/widgetbox/gallery-image.html
widgetbox/templates/widgetbox/gallery.html
widgetbox/templates/widgetbox/html.html
widgetbox/templates/widgetbox/list-item.html
widgetbox/templates/widgetbox/list.html
widgetbox/templates/widgetbox/ol.html
widgetbox/templates/widgetbox/quote.html
widgetbox/templates/widgetbox/row.html
widgetbox/templates/widgetbox/tab-pane.html
widgetbox/templates/widgetbox/tab.html
widgetbox/templates/widgetbox/ul.html