Metadata-Version: 1.1
Name: djangocms-widgetbox
Version: 0.9.0
Summary: djangocms plugin that implements few small widgets
Home-page: https://github.com/logithr/djangocms-widgetbox
Author: Sasha Matijasic
Author-email: sasha@selectnull.com
License: MIT
Platform: UNKNOWN
Classifier: Development Status :: 3 - Alpha
Classifier: Environment :: Web Environment
Classifier: Framework :: Django
Classifier: Intended Audience :: Developers
Classifier: License :: OSI Approved :: MIT License
Classifier: Operating System :: OS Independent
Classifier: Programming Language :: Python
Classifier: Programming Language :: Python :: 2
Classifier: Programming Language :: Python :: 2.7
Classifier: Topic :: Internet :: WWW/HTTP :: Dynamic Content
